clickhouse_bundle/__init__.py
clickhouse_bundle/bundle.py
clickhouse_bundle-1.0.dist-info/LICENSE
clickhouse_bundle-1.0.dist-info/METADATA
clickhouse_bundle-1.0.dist-info/WHEEL
clickhouse_bundle-1.0.dist-info/top_level.txt
clickhouse_bundle-1.0.dist-info/RECORD
