Metadata-Version: 2.1
Name: clickhouse-bundle
Version: 1.0
Summary: Clickhouse support for applauncher
Home-page: https://github.com/applauncher-team/clickhouse_bundle
Author: Alvaro Garcia Gomez
Author-email: maxpowel@gmail.com
License: UNKNOWN
Download-URL: https://github.com/applauncher-team/clickhouse_bundle/archive/master.zip
Keywords: applauncher,clickhouse
Platform: UNKNOWN
Classifier: Topic :: Adaptive Technologies
Classifier: Topic :: Software Development
Classifier: Topic :: System
Classifier: Topic :: Utilities
Requires-Dist: applauncher (==1.44)
Requires-Dist: clickhouse-driver (==0.1.4)
